README.md
setup.cfg
setup.py
pyCx/__init__.py
pyCx/cx.py
pyCx/cx_config.py
pyCx/cx_filter.py
pyCx/cx_query.py
pyCx/cx_url.py
pyCx/decorators.py
pyCx/helpers.py
pyCx.egg-info/PKG-INFO
pyCx.egg-info/SOURCES.txt
pyCx.egg-info/dependency_links.txt
pyCx.egg-info/requires.txt
pyCx.egg-info/top_level.txt